{
  "cookies": [
    {
      "name": "CookieConsentPolicy",
      "value": "0:0",
      "domain": "login.salesforce.com",
      "path": "/",
      "expires": 1806460438.336561,
      "httpOnly": false,
      "secure": true,
      "sameSite": "Lax"
    },
    {
      "name": "LSKey-c$CookieConsentPolicy",
      "value": "0:0",
      "domain": "login.salesforce.com",
      "path": "/",
      "expires": 1806460438.33681,
      "httpOnly": false,
      "secure": true,
      "sameSite": "Lax"
    },
    {
      "name": "BrowserId",
      "value": "EbIOHiyqEfGEL0dTKpJl4w",
      "domain": ".salesforce.com",
      "path": "/",
      "expires": 1806460438.336891,
      "httpOnly": false,
      "secure": true,
      "sameSite": "None"
    },
    {
      "name": "session",
      "value": "1774924439520",
      "domain": "login.salesforce.com",
      "path": "/",
      "expires": -1,
      "httpOnly": false,
      "secure": true,
      "sameSite": "None"
    },
    {
      "name": "sfdcConsent",
      "value": "1%2C3%2C4",
      "domain": ".salesforce.com",
      "path": "/",
      "expires": 1806460440,
      "httpOnly": false,
      "secure": false,
      "sameSite": "Lax"
    },
    {
      "name": "gtm_session_start",
      "value": "1774924440503",
      "domain": "c.salesforce.com",
      "path": "/",
      "expires": 1774926240,
      "httpOnly": false,
      "secure": false,
      "sameSite": "Lax"
    },
    {
      "name": "_ga",
      "value": "GA1.1.366644799.1774924443",
      "domain": ".salesforce.com",
      "path": "/",
      "expires": 1809484442.6553,
      "httpOnly": false,
      "secure": false,
      "sameSite": "Lax"
    },
    {
      "name": "_ga_S6WMKB0ZK3",
      "value": "GS2.1.s1774924441$o1$g0$t1774924441$j60$l0$h0",
      "domain": ".salesforce.com",
      "path": "/",
      "expires": 1809484442.694877,
      "httpOnly": false,
      "secure": false,
      "sameSite": "Lax"
    },
    {
      "name": "_gcl_au",
      "value": "1.1.1329173448.1774924443",
      "domain": ".salesforce.com",
      "path": "/",
      "expires": 1782700443,
      "httpOnly": false,
      "secure": false,
      "sameSite": "Lax"
    },
    {
      "name": "IDE",
      "value": "AHWqTUngwymHH1z5HDx_KrfxRagZHFIGcLt0UmMAfWpaWd90IOHk0AAZUZ-9q4gs",
      "domain": ".doubleclick.net",
      "path": "/",
      "expires": 1809484442.971889,
      "httpOnly": true,
      "secure": true,
      "sameSite": "None"
    },
    {
      "name": "OptanonConsent",
      "value": "isGpcEnabled=0&datestamp=Tue+Mar+31+2026+08%3A04%3A06+GMT%2B0530+(India+Standard+Time)&version=202408.1.0&browserGpcFlag=0&isIABGlobal=false&hosts=&consentId=f0cbc6ac-167f-43bb-a28a-15a8fb17563d&interactionCount=1&isAnonUser=1&landingPath=https%3A%2F%2Fc.salesforce.com%2Flogin-messages%2Fin%2Fpromos.html&groups=1%3A1%2C3%3A1%2C4%3A1",
      "domain": ".salesforce.com",
      "path": "/",
      "expires": 1806460446,
      "httpOnly": false,
      "secure": false,
      "sameSite": "Lax"
    },
    {
      "name": "inst",
      "value": "APP_NS",
      "domain": ".salesforce.com",
      "path": "/",
      "expires": -1,
      "httpOnly": false,
      "secure": true,
      "sameSite": "Lax"
    },
    {
      "name": "rememberUn",
      "value": "false",
      "domain": ".salesforce.com",
      "path": "/",
      "expires": 1780108447.196443,
      "httpOnly": false,
      "secure": true,
      "sameSite": "Lax"
    },
    {
      "name": "com.salesforce.LocaleInfo",
      "value": "in",
      "domain": ".salesforce.com",
      "path": "/",
      "expires": 1780108447.196517,
      "httpOnly": false,
      "secure": true,
      "sameSite": "Lax"
    },
    {
      "name": "oinfo",
      "value": "c3RhdHVzPUZSRUUmdHlwZT0zJm9pZD0wMEROUzAwMDAwMXJUQVg=",
      "domain": ".salesforce.com",
      "path": "/",
      "expires": 1780108447.196561,
      "httpOnly": false,
      "secure": true,
      "sameSite": "Lax"
    },
    {
      "name": "CookieConsentPolicy",
      "value": "0:1",
      "domain": "testleaf22-dev-ed.develop.my.salesforce.com",
      "path": "/",
      "expires": 1806460447.395029,
      "httpOnly": false,
      "secure": true,
      "sameSite": "None"
    },
    {
      "name": "LSKey-c$CookieConsentPolicy",
      "value": "0:1",
      "domain": "testleaf22-dev-ed.develop.my.salesforce.com",
      "path": "/",
      "expires": 1806460447.395117,
      "httpOnly": false,
      "secure": true,
      "sameSite": "None"
    },
    {
      "name": "disco",
      "value": "NS:00DNS000001rTAX:005NS000001C9hO:3",
      "domain": ".salesforce.com",
      "path": "/",
      "expires": -1,
      "httpOnly": false,
      "secure": true,
      "sameSite": "None"
    },
    {
      "name": "autocomplete",
      "value": "1",
      "domain": ".salesforce.com",
      "path": "/",
      "expires": 1780108447.395206,
      "httpOnly": false,
      "secure": true,
      "sameSite": "None"
    },
    {
      "name": "sid",
      "value": "00DNS000001rTAX!AQEAQIowSKgO13Xjul_KTkgC8ZzyyrUPaYdUQCJwFBVtZYR7P.wm_3jMOkeFHQis.RNBQSLNTSVCPHWxJ5BFloC_wUAgpMIE",
      "domain": "testleaf22-dev-ed.develop.my.salesforce.com",
      "path": "/",
      "expires": -1,
      "httpOnly": false,
      "secure": true,
      "sameSite": "None"
    },
    {
      "name": "sid_Client",
      "value": "S000001C9hOS000001rTAX",
      "domain": "testleaf22-dev-ed.develop.my.salesforce.com",
      "path": "/",
      "expires": -1,
      "httpOnly": false,
      "secure": true,
      "sameSite": "None"
    },
    {
      "name": "clientSrc",
      "value": "183.82.205.240",
      "domain": "testleaf22-dev-ed.develop.my.salesforce.com",
      "path": "/",
      "expires": -1,
      "httpOnly": false,
      "secure": true,
      "sameSite": "None"
    },
    {
      "name": "oid",
      "value": "00DNS000001rTAX",
      "domain": "testleaf22-dev-ed.develop.my.salesforce.com",
      "path": "/",
      "expires": 1806460447.395336,
      "httpOnly": false,
      "secure": true,
      "sameSite": "None"
    },
    {
      "name": "79eb100099b9a8bf",
      "value": "3:false:.develop.my.salesforce.com",
      "domain": ".develop.my.salesforce.com",
      "path": "/",
      "expires": -1,
      "httpOnly": false,
      "secure": true,
      "sameSite": "None"
    },
    {
      "name": "sfdc_lv2",
      "value": "KxG83HLbUVlkUZl3I8iMCUtzYJ9M+YqubjYX5z57b+m7ta/2cZ7L5l96SHawBzaWU=",
      "domain": ".salesforce.com",
      "path": "/",
      "expires": 1806460461.431416,
      "httpOnly": false,
      "secure": true,
      "sameSite": "None"
    },
    {
      "name": "CookieConsentPolicy",
      "value": "0:1",
      "domain": "testleaf22-dev-ed.develop.file.force.com",
      "path": "/",
      "expires": 1806460462.027104,
      "httpOnly": false,
      "secure": true,
      "sameSite": "None"
    },
    {
      "name": "LSKey-c$CookieConsentPolicy",
      "value": "0:1",
      "domain": "testleaf22-dev-ed.develop.file.force.com",
      "path": "/",
      "expires": 1806460462.027497,
      "httpOnly": false,
      "secure": true,
      "sameSite": "None"
    },
    {
      "name": "BrowserId",
      "value": "H8whQiyqEfGHnYeqqmDYaA",
      "domain": ".force.com",
      "path": "/",
      "expires": 1806460462.02772,
      "httpOnly": false,
      "secure": true,
      "sameSite": "None"
    },
    {
      "name": "sid",
      "value": "00DNS000001rTAX!AQEAQCXLIInCyvtnq6AtJe_YbB_S1OQWA7Kb6BmqAQwMd5wn9XjACs98YOKykDdeuZBw2XFPHrsLLkvXr_QCxC5gVcCqQsh8",
      "domain": "testleaf22-dev-ed.develop.file.force.com",
      "path": "/",
      "expires": -1,
      "httpOnly": false,
      "secure": true,
      "sameSite": "None"
    },
    {
      "name": "sid_Client",
      "value": "S000001C9hOS000001rTAX",
      "domain": "testleaf22-dev-ed.develop.file.force.com",
      "path": "/",
      "expires": -1,
      "httpOnly": false,
      "secure": true,
      "sameSite": "None"
    },
    {
      "name": "clientSrc",
      "value": "183.82.205.240",
      "domain": "testleaf22-dev-ed.develop.file.force.com",
      "path": "/",
      "expires": -1,
      "httpOnly": false,
      "secure": true,
      "sameSite": "None"
    },
    {
      "name": "inst",
      "value": "APP_NS",
      "domain": ".force.com",
      "path": "/",
      "expires": -1,
      "httpOnly": false,
      "secure": true,
      "sameSite": "None"
    },
    {
      "name": "CookieConsentPolicy",
      "value": "0:1",
      "domain": "testleaf22-dev-ed.develop.lightning.force.com",
      "path": "/",
      "expires": 1806460462.391685,
      "httpOnly": false,
      "secure": true,
      "sameSite": "None"
    },
    {
      "name": "LSKey-c$CookieConsentPolicy",
      "value": "0:1",
      "domain": "testleaf22-dev-ed.develop.lightning.force.com",
      "path": "/",
      "expires": 1806460462.391837,
      "httpOnly": false,
      "secure": true,
      "sameSite": "None"
    },
    {
      "name": "sid",
      "value": "00DNS000001rTAX!AQEAQOU7b5uk4f_dD3ERbvX_Eab.ZUXyC7Ee5SsRlF7mCkQG3jzFk7pKJAMMolrpbikutYTaZ0hhN9VBOOxEvK22kr6pwa1f",
      "domain": "testleaf22-dev-ed.develop.lightning.force.com",
      "path": "/",
      "expires": -1,
      "httpOnly": false,
      "secure": true,
      "sameSite": "None"
    },
    {
      "name": "sid_Client",
      "value": "S000001C9hOS000001rTAX",
      "domain": "testleaf22-dev-ed.develop.lightning.force.com",
      "path": "/",
      "expires": -1,
      "httpOnly": false,
      "secure": true,
      "sameSite": "None"
    },
    {
      "name": "clientSrc",
      "value": "183.82.205.240",
      "domain": "testleaf22-dev-ed.develop.lightning.force.com",
      "path": "/",
      "expires": -1,
      "httpOnly": false,
      "secure": true,
      "sameSite": "None"
    },
    {
      "name": "79eb100099b9a8bf",
      "value": "3:false:.develop.lightning.force.com",
      "domain": ".develop.lightning.force.com",
      "path": "/",
      "expires": -1,
      "httpOnly": false,
      "secure": true,
      "sameSite": "None"
    },
    {
      "name": "CookieConsentPolicy",
      "value": "0:1",
      "domain": "testleaf22-dev-ed.develop.my.salesforce-setup.com",
      "path": "/",
      "expires": 1806460463.468223,
      "httpOnly": false,
      "secure": true,
      "sameSite": "None"
    },
    {
      "name": "LSKey-c$CookieConsentPolicy",
      "value": "0:1",
      "domain": "testleaf22-dev-ed.develop.my.salesforce-setup.com",
      "path": "/",
      "expires": 1806460463.468302,
      "httpOnly": false,
      "secure": true,
      "sameSite": "None"
    },
    {
      "name": "SetupDomainProbePassed",
      "value": "true",
      "domain": "testleaf22-dev-ed.develop.lightning.force.com",
      "path": "/",
      "expires": -1,
      "httpOnly": false,
      "secure": true,
      "sameSite": "None"
    },
    {
      "name": "sid",
      "value": "00DNS000001rTAX!AQEAQPI3empBnGjvRvmPuA.vNnDw0xIkUqbsKfcNMqSYB8sKyusLrE0Tdwos1Esi7pxjHJF89PgokeIBd4I73HLMzLa.2WjQ",
      "domain": "testleaf22-dev-ed.develop.my.salesforce-setup.com",
      "path": "/",
      "expires": -1,
      "httpOnly": false,
      "secure": true,
      "sameSite": "None"
    },
    {
      "name": "sid_Client",
      "value": "S000001C9hOS000001rTAX",
      "domain": "testleaf22-dev-ed.develop.my.salesforce-setup.com",
      "path": "/",
      "expires": -1,
      "httpOnly": false,
      "secure": true,
      "sameSite": "None"
    },
    {
      "name": "clientSrc",
      "value": "183.82.205.240",
      "domain": "testleaf22-dev-ed.develop.my.salesforce-setup.com",
      "path": "/",
      "expires": -1,
      "httpOnly": false,
      "secure": true,
      "sameSite": "None"
    },
    {
      "name": "inst",
      "value": "APP_NS",
      "domain": "testleaf22-dev-ed.develop.my.salesforce-setup.com",
      "path": "/",
      "expires": -1,
      "httpOnly": false,
      "secure": true,
      "sameSite": "None"
    },
    {
      "name": "79eb100099b9a8bf",
      "value": "3:false:.develop.my.salesforce-setup.com",
      "domain": ".develop.my.salesforce-setup.com",
      "path": "/",
      "expires": -1,
      "httpOnly": false,
      "secure": true,
      "sameSite": "None"
    },
    {
      "name": "SetupDomainProbePassed",
      "value": "true",
      "domain": "testleaf22-dev-ed.develop.my.salesforce-setup.com",
      "path": "/",
      "expires": -1,
      "httpOnly": false,
      "secure": true,
      "sameSite": "None"
    }
  ],
  "origins": [
    {
      "origin": "https://testleaf22-dev-ed.develop.my.salesforce-setup.com",
      "localStorage": [
        {
          "name": "$AuraClientService.token$one:one",
          "value": "eyJub25jZSI6IkU2LXRjd3hybzVQLTlwU0dmTDdSNzI1QjZaN2RDMllTbHFyV1hrZUpFeDBcdTAwM2QiLCJ0eXAiOiJKV1QiLCJhbGciOiJIUzI1NiIsImtpZCI6IntcInRcIjpcIjAwRE5TMDAwMDAwMDAwMVwiLFwidlwiOlwiMDJHTlMwMDAwMDAwMDFkXCIsXCJhXCI6XCJjYWltYW5zaWduZXJcIn0iLCJjcml0IjpbImlhdCJdLCJpYXQiOjE3NzQ5MjQ0NjM1MDIsImV4cCI6MH0=..UejQRUDLu_2BRI7BrK_a--jsiN-yHnl71492xTnFS54="
        },
        {
          "name": "setupAppContextId",
          "value": "all"
        },
        {
          "name": "GlobalValueProviders__MUTEX_X",
          "value": "9655000007f8b9e9748298|1774924466363"
        },
        {
          "name": "disableAppSwitcherClosingGate",
          "value": "false"
        }
      ]
    },
    {
      "origin": "https://c.salesforce.com",
      "localStorage": [
        {
          "name": "_gcl_ls",
          "value": "{\"schema\":\"gcl\",\"version\":1,\"gcl_ctr\":{\"value\":{\"value\":0,\"timeouts\":0,\"errors\":0,\"creationTimeMs\":1774924442704},\"expires\":1782700442704}}"
        }
      ]
    },
    {
      "origin": "https://testleaf22-dev-ed.develop.lightning.force.com",
      "localStorage": [
        {
          "name": "$AuraClientService.token$one:one",
          "value": "eyJub25jZSI6InE1dXR4ZG5oWFkyVmpUWVlxdTVHLVpLc3BuZUM3UEhPaFVFX0lZRkFHcU1cdTAwM2QiLCJ0eXAiOiJKV1QiLCJhbGciOiJIUzI1NiIsImtpZCI6IntcInRcIjpcIjAwRE5TMDAwMDAwMDAwMVwiLFwidlwiOlwiMDJHTlMwMDAwMDAwMDFkXCIsXCJhXCI6XCJjYWltYW5zaWduZXJcIn0iLCJjcml0IjpbImlhdCJdLCJpYXQiOjE3NzQ5MjQ0NjIzMDcsImV4cCI6MH0=..WL3g5Y5ODaKsGET2lQOqfnS-3KLyel315pC3ZS0GSNA="
        },
        {
          "name": "setupAppContextId",
          "value": "all"
        },
        {
          "name": "GlobalValueProviders__MUTEX_X",
          "value": "7448000005f84a518724828|1774924463810"
        },
        {
          "name": "GlobalValueProviders__MUTEX_Y",
          "value": "7448000005f84a518724828|1774924463836"
        }
      ]
    }
  ]
}